USBdev/__init__.py
USBdev/__metadata__.py
USBdev/main.py
usbdev-2019.11.5.data/scripts/usbdev
var/lib/usbdev/usb.ids
usbdev-2019.11.5.dist-info/LICENSE
usbdev-2019.11.5.dist-info/METADATA
usbdev-2019.11.5.dist-info/WHEEL
usbdev-2019.11.5.dist-info/top_level.txt
usbdev-2019.11.5.dist-info/RECORD
