Metadata-Version: 2.1
Name: usbdev
Version: 2019.11.5
Summary: USBdev is a tool recognition of USB devices
Home-page: https://gitlab.com/dslackw/USBdev
Author: dslackw
Author-email: d.zlatanidis@gmail.com
License: UNKNOWN
Keywords: usb,device
Platform: UNKNOWN
Classifier: Development Status :: 5 - Production/Stable
Classifier: License :: OSI Approved :: GNU General Public License v3 or later (GPLv3+)
Classifier: Operating System :: POSIX :: Linux
Classifier: Operating System :: Unix
Classifier: Programming Language :: Python :: 3
Requires-Python: >=3.7
Requires-Dist: pyusb (>=1.0.0)
